ttrans/__init__.py
ttrans/app.py
ttrans/cli.py
ttrans/first_run.py
ttrans-0.1.1.dist-info/METADATA
ttrans-0.1.1.dist-info/WHEEL
ttrans-0.1.1.dist-info/entry_points.txt
ttrans-0.1.1.dist-info/licenses/LICENSE
ttrans-0.1.1.dist-info/RECORD
