Metadata-Version: 2.4
Name: ttrans
Version: 0.1.1
Summary: macOS meeting transcription assistant with TUI
Project-URL: Homepage, https://github.com/adnichols/ttrans
Project-URL: Repository, https://github.com/adnichols/ttrans
Project-URL: Bug Tracker, https://github.com/adnichols/ttrans/issues
Author-email: Aaron Nichols <adnichols@users.noreply.github.com>
License-Expression: MIT
License-File: LICENSE
Keywords: audio,macos,meeting,transcription,tui,whisper
Classifier: Development Status :: 4 - Beta
Classifier: Environment :: Console
Classifier: Intended Audience :: End Users/Desktop
Classifier: License :: OSI Approved :: MIT License
Classifier: Operating System :: MacOS :: MacOS X
Classifier: Programming Language :: Python :: 3
Classifier: Programming Language :: Python :: 3.11
Classifier: Programming Language :: Python :: 3.12
Classifier: Topic :: Multimedia :: Sound/Audio :: Capture/Recording
Classifier: Topic :: Multimedia :: Sound/Audio :: Speech
Requires-Python: >=3.11
Requires-Dist: mlx-whisper>=0.4.0
Requires-Dist: numpy>=2.3.5
Requires-Dist: openai>=2.8.1
Requires-Dist: pyobjc>=12.1
Requires-Dist: scipy>=1.11.0
Requires-Dist: sounddevice>=0.5.3
Requires-Dist: textual>=6.7.1
Requires-Dist: tomli-w>=1.2.0
